piston_v_taper/__init__.py
piston_v_taper/data_sets.py
piston_v_taper/example.py
piston_v_taper/example_against_data.py
piston_v_taper/model.py
piston_v_taper/nns.py
piston_v_taper/plotting_config.py
piston_v_taper/data/__init__.py
piston_v_taper/data/contact_mid_dim_8_n_hidden_0.pth
piston_v_taper/data/elastic_mid_dim_3_n_hidden_0.pth
piston_v_taper/data/elastoplastic_mid_dim_3_n_hidden_0.pth
piston_v_taper/data/processed_test_data.csv
piston_v_taper-0.1.1.dist-info/LICENSE
piston_v_taper-0.1.1.dist-info/METADATA
piston_v_taper-0.1.1.dist-info/WHEEL
piston_v_taper-0.1.1.dist-info/top_level.txt
piston_v_taper-0.1.1.dist-info/RECORD
