Metadata-Version: 2.1
Name: piston-v-taper
Version: 0.1.1
Summary: A trained machine learning model for predicting the force due to contact between a deformable end cap and a taper
Home-page: https://github.com/BenAlheit/piston-vs-taper
Author: Benjamin Alheit
Author-email: alhben001@myuct.ac.za
License: UNKNOWN
Platform: UNKNOWN
Classifier: Programming Language :: Python :: 3
Classifier: License :: OSI Approved :: MIT License
Classifier: Operating System :: OS Independent
Requires-Python: >=3.6
License-File: LICENSE
Requires-Dist: aiohttp (==3.7.4.post0)
Requires-Dist: async-timeout (==3.0.1)
Requires-Dist: attrs (==21.2.0)
Requires-Dist: bleach (==4.1.0)
Requires-Dist: build (==0.7.0)
Requires-Dist: certifi (==2021.5.30)
Requires-Dist: chardet (==4.0.0)
Requires-Dist: colorama (==0.4.4)
Requires-Dist: cycler (==0.10.0)
Requires-Dist: dateparser (==1.0.0)
Requires-Dist: docutils (==0.17.1)
Requires-Dist: idna (==2.10)
Requires-Dist: importlib-metadata (==4.8.1)
Requires-Dist: joblib (==1.1.0)
Requires-Dist: keyring (==23.2.1)
Requires-Dist: kiwisolver (==1.3.2)
Requires-Dist: matplotlib (==3.4.3)
Requires-Dist: multidict (==5.1.0)
Requires-Dist: numpy (==1.21.2)
Requires-Dist: packaging (==21.0)
Requires-Dist: pandas (==1.3.3)
Requires-Dist: pep517 (==0.11.0)
Requires-Dist: Pillow (==8.3.2)
Requires-Dist: pkginfo (==1.7.1)
Requires-Dist: Pygments (==2.10.0)
Requires-Dist: pyparsing (==2.4.7)
Requires-Dist: python-binance (==1.0.12)
Requires-Dist: python-dateutil (==2.8.1)
Requires-Dist: pytz (==2021.1)
Requires-Dist: pywin32-ctypes (==0.2.0)
Requires-Dist: readme-renderer (==30.0)
Requires-Dist: regex (==2021.4.4)
Requires-Dist: requests (==2.25.1)
Requires-Dist: requests-toolbelt (==0.9.1)
Requires-Dist: rfc3986 (==1.5.0)
Requires-Dist: scikit-learn (==1.0)
Requires-Dist: scipy (==1.7.1)
Requires-Dist: seaborn (==0.11.2)
Requires-Dist: six (==1.16.0)
Requires-Dist: sklearn (==0.0)
Requires-Dist: threadpoolctl (==3.0.0)
Requires-Dist: tomli (==1.2.1)
Requires-Dist: torch (==1.9.1)
Requires-Dist: tqdm (==4.62.3)
Requires-Dist: twine (==3.4.2)
Requires-Dist: typing-extensions (==3.10.0.0)
Requires-Dist: tzlocal (==2.1)
Requires-Dist: ujson (==4.0.2)
Requires-Dist: urllib3 (==1.26.5)
Requires-Dist: webencodings (==0.5.1)
Requires-Dist: websockets (==9.1)
Requires-Dist: wincertstore (==0.2)
Requires-Dist: yarl (==1.6.3)
Requires-Dist: zipp (==3.6.0)
